specgfx/__init__.py
specgfx/cyrender.cp37-win_amd64.pyd
specgfx/specgfx.py
specgfx-0.0.1.dev4.dist-info/LICENSE
specgfx-0.0.1.dev4.dist-info/METADATA
specgfx-0.0.1.dev4.dist-info/WHEEL
specgfx-0.0.1.dev4.dist-info/top_level.txt
specgfx-0.0.1.dev4.dist-info/RECORD
