Metadata-Version: 2.1
Name: specgfx
Version: 0.0.1.dev4
Summary: ZX spectrum inspired text and graphics
Home-page: https://github.com/ptc24/specgfx/
Author: Peter Corbett
Author-email: peter.corbett@cantab.net
License: UNKNOWN
Platform: UNKNOWN
Requires-Dist: numpy
Requires-Dist: pygame
Requires-Dist: cython
